{
  "ftp://103.167.199.37@vieclam@vieclam24.com.vn": {
    "public_html": {
      "wp-content": {
        "themes": {
          "vieclam24": {
            "404.php": {
              "type": "-",
              "size": 658,
              "lmtime": 0,
              "modified": false
            },
            "LICENSE": {
              "type": "-",
              "size": 15410,
              "lmtime": 0,
              "modified": false
            },
            "README.md": {
              "type": "-",
              "size": 2278,
              "lmtime": 0,
              "modified": false
            },
            "app": {},
            "archive-loop.php": {
              "type": "-",
              "size": 649,
              "lmtime": 0,
              "modified": false
            },
            "archive.php": {
              "type": "-",
              "size": 882,
              "lmtime": 0,
              "modified": false
            },
            "assets": {},
            "author-bio.php": {
              "type": "-",
              "size": 1873,
              "lmtime": 0,
              "modified": false
            },
            "author.php": {
              "type": "-",
              "size": 920,
              "lmtime": 0,
              "modified": false
            },
            "build": {},
            "category.php": {
              "type": "-",
              "size": 723,
              "lmtime": 0,
              "modified": false
            },
            "comments.php": {
              "type": "-",
              "size": 3068,
              "lmtime": 0,
              "modified": false
            },
            "content-index.php": {
              "type": "-",
              "size": 1876,
              "lmtime": 0,
              "modified": false
            },
            "content-none.php": {
              "type": "-",
              "size": 683,
              "lmtime": 0,
              "modified": false
            },
            "content-single.php": {
              "type": "-",
              "size": 2380,
              "lmtime": 0,
              "modified": false
            },
            "content.php": {
              "type": "-",
              "size": 3368,
              "lmtime": 0,
              "modified": false
            },
            "footer.php": {
              "type": "-",
              "size": 2267,
              "lmtime": 0,
              "modified": false
            },
            "functions.php": {
              "type": "-",
              "size": 167,
              "lmtime": 0,
              "modified": true
            },
            "header.php": {
              "type": "-",
              "size": 3581,
              "lmtime": 0,
              "modified": false
            },
            "image.php": {
              "type": "-",
              "size": 2749,
              "lmtime": 0,
              "modified": false
            },
            "inc": {
              "class-wep-functions.php": {
                "type": "-",
                "size": 21327,
                "lmtime": 1699543844196,
                "modified": false
              },
              "customizer.js": {
                "type": "-",
                "size": 999,
                "lmtime": 0,
                "modified": false
              },
              "customizer.php": {
                "type": "-",
                "size": 3538,
                "lmtime": 0,
                "modified": false
              },
              "wp-bootstrap-navwalker-footer.php": {
                "type": "-",
                "size": 2861,
                "lmtime": 0,
                "modified": false
              },
              "wp-bootstrap-navwalker.php": {
                "type": "-",
                "size": 9114,
                "lmtime": 0,
                "modified": false
              }
            },
            "index.php": {
              "type": "-",
              "size": 605,
              "lmtime": 0,
              "modified": false
            },
            "languages": {},
            "package.json": {
              "type": "-",
              "size": 654,
              "lmtime": 0,
              "modified": false
            },
            "page-full.php": {
              "type": "-",
              "size": 866,
              "lmtime": 0,
              "modified": false
            },
            "page-nosidebar.php": {
              "type": "-",
              "size": 871,
              "lmtime": 0,
              "modified": false
            },
            "page.php": {
              "type": "-",
              "size": 1080,
              "lmtime": 0,
              "modified": false
            },
            "readme.txt": {
              "type": "-",
              "size": 1360,
              "lmtime": 0,
              "modified": false
            },
            "screenshot.jpg": {
              "type": "-",
              "size": 819728,
              "lmtime": 1699440348458,
              "modified": false
            },
            "search.php": {
              "type": "-",
              "size": 825,
              "lmtime": 0,
              "modified": false
            },
            "searchform.php": {
              "type": "-",
              "size": 476,
              "lmtime": 0,
              "modified": false
            },
            "sidebar.php": {
              "type": "-",
              "size": 2682,
              "lmtime": 0,
              "modified": false
            },
            "single.php": {
              "type": "-",
              "size": 1570,
              "lmtime": 0,
              "modified": false
            },
            "style-editor.css": {
              "type": "-",
              "size": 90,
              "lmtime": 0,
              "modified": false
            },
            "style.css": {
              "type": "-",
              "size": 3962,
              "lmtime": 0,
              "modified": false
            },
            "tag.php": {
              "type": "-",
              "size": 675,
              "lmtime": 0,
              "modified": false
            },
            "webpack.config.js": {
              "type": "-",
              "size": 973,
              "lmtime": 0,
              "modified": false
            }
          }
        }
      }
    }
  },
  "$version": 1
}